bqsc/__init__.py
bqsc/cli.py
bqsc/column_info.py
bqsc/load.py
bqsc/py.typed
bqsc/table.py
bqsc/table_info.py
bqsc/type_map.py
bqsc-5.0.1.dist-info/entry_points.txt
bqsc-5.0.1.dist-info/LICENSE
bqsc-5.0.1.dist-info/WHEEL
bqsc-5.0.1.dist-info/METADATA
bqsc-5.0.1.dist-info/RECORD
