Metadata-Version: 2.1
Name: bqsc
Version: 5.0.1
Summary: Define schema object from bigquery schema definition json file
License: MIT
Author: Yasunori Horikoshi
Author-email: hotoku@users.noreply.github.com
Requires-Python: >=3.9,<3.11
Classifier: License :: OSI Approved :: MIT License
Classifier: Programming Language :: Python :: 3
Classifier: Programming Language :: Python :: 3.9
Requires-Dist: click (>=8.0.3,<9.0.0)
Requires-Dist: mypy (>=0.910,<0.911)
Requires-Dist: pandas (>=1.3.4,<2.0.0)
Requires-Dist: pandas-gbq (>=0.17.1,<0.18.0)
